openctp_tts_6319/__about__.py
openctp_tts_6319/__init__.py
openctp_tts_6319/thostmduserapi.py
openctp_tts_6319/thosttraderapi.py
openctp_tts_6319/_thostmduserapi.pyd
openctp_tts_6319/_thosttraderapi.pyd
openctp_tts_6319/thostmduserapi_se.dll
openctp_tts_6319/thosttraderapi_se.dll
openctp_tts_6319-0.0.2.dist-info/METADATA
openctp_tts_6319-0.0.2.dist-info/WHEEL
openctp_tts_6319-0.0.2.dist-info/licenses/LICENSE
openctp_tts_6319-0.0.2.dist-info/RECORD
