Metadata-Version: 2.1
Name: openctp-tts-6319
Version: 0.0.2
Summary: A package for TTS-6.3.19
Project-URL: Source, https://github.com/Jedore/openctp-tts-python
Project-URL: Issues, https://github.com/Jedore/openctp-tts-python/issues
Project-URL: Openctp, https://github.com/openctp/openctp
Author-email: Jedore <jedore@protonmail.com>
Maintainer-email: Jedore <jedore@protonmail.com>
License-Expression: MIT
License-File: LICENSE
Keywords: ctp,ctpapi,investment,openctp,trading,tts
Classifier: License :: OSI Approved :: MIT License
Classifier: Natural Language :: Chinese (Simplified)
Classifier: Operating System :: MacOS
Classifier: Operating System :: Microsoft :: Windows
Classifier: Operating System :: POSIX :: Linux
Classifier: Programming Language :: Python :: 3
Classifier: Programming Language :: Python :: 3.7
Classifier: Programming Language :: Python :: 3.8
Classifier: Programming Language :: Python :: 3.9
Classifier: Programming Language :: Python :: 3.10
Classifier: Programming Language :: Python :: 3.11
Classifier: Programming Language :: Python :: Implementation :: CPython
Classifier: Topic :: Office/Business :: Financial :: Investment
Requires-Python: >=3.7
